nightingaleews/__init__.py
nightingaleews/ews_scorer.py
nightingaleews-2.0.0.dist-info/METADATA
nightingaleews-2.0.0.dist-info/WHEEL
nightingaleews-2.0.0.dist-info/top_level.txt
nightingaleews-2.0.0.dist-info/RECORD
