Metadata-Version: 2.1
Name: nightingaleews
Version: 2.0.0
Summary: Early Warning Score Calculator
Author: Nuno Antunes
Author-email: <nuno.f.antunes@inov.pt>
Keywords: earlywarningscore
